tgraphics/__init__.py
tgraphics/chars.py
tgraphics/errors.py
tgraphics/screen.py
tgraphics/sprite.py
tgraphics/std.py
tgraphics/texture.py
tgraphics/vector.py
tgraphics/readchar/__init__.py
tgraphics/readchar/key.py
tgraphics/readchar/readchar.py
tgraphics/readchar/readchar_linux.py
tgraphics/readchar/readchar_windows.py
tgraphics-1.0.1.dist-info/METADATA
tgraphics-1.0.1.dist-info/WHEEL
tgraphics-1.0.1.dist-info/top_level.txt
tgraphics-1.0.1.dist-info/RECORD
