Metadata-Version: 2.1
Name: tgraphics
Version: 1.0.1
Summary: An omni-platform terminal graphics module
Home-page: https://repl.it/@GrandMoff100/tgraphics
Author: Wizard
Author-email: nlarsen23.student@gmail.com
License: UNKNOWN
Platform: UNKNOWN
Requires-Dist: colorama
